{
    "Математика 10 клас": "images/math-10.jpg",
    "Математика 11 клас": "images/math-11.jpg",
    "Історія України": "images/history-of-Ukraine.jpg",
    "Хімія": "images/chemistry.jpg",
    "Фізика, Засєкіни": "images/physics-Zaseciny.jpg",
    "Фізика, Баряхтар": "images/physics-Barjakhtar.jpeg",
    "Всесвітня Історія": "images/world-history.jpeg",
    "Українська мова": "images/ukrainian-language.jpg",
    "Астрономія": "images/physics-Barjakhtar.jpeg",
    "Біологія": "images/biology.jpg",
    "Географія": "images/geography.jpg",
    "Зарубіжна література": "images/foreign-literature.jpg",
    "Українська література": "images/ukrainian-literature.jpg",
    "Захист України": "images/defending-Ukraine.jpg",
    "Інформатика": "images/informatics.webp"
}